counter.v
module counter(
    input clk,
    input rst,
    output reg count_done
);

reg [7:0] cnt;

always @ (posedge clk) begin
    if(rst) cnt <= 8'd0;
    else if(cnt >= 8'd10) cnt <= 8'd0;
    else cnt <= cnt + 8'd1;
end

always @ (posedge clk) begin
    if(rst)
        count_done <= 1'b0;
    else if(cnt == 8'd10)
        count_done <= 1'b1;
    else
        count_done <= 1'b0;
end

endmodule

tb_counter.v
`timescale 1ns/100ps
`include "counter.v" //加了比較保險，讓tb能讀到top module
module tb_counter;

parameter CLK_PERIOD = 10;

reg  CLK;
reg  RESET;
wire count_done;
//module be tested
counter t0 (
    .rst(RESET),
    .clk(CLK),
    .count_done(count_done)
);
//stimilu
initial begin
    CLK   = 1'b0;
    RESET = 1'b1;
end

initial begin
    #100
        RESET = 1'b0;
    #1000
        $finish;
end

always @(CLK)
    #(CLK_PERIOD/2) CLK <= !CLK;

/*iverilog */
initial begin            
    $dumpfile("wave.vcd");       //產生vcd name
    $dumpvars(0, tb_counter);    //tb module name
end

endmodule

wave.vcd
$date
	Sat Sep 20 18:59:35 2025
$end
$version
	Icarus Verilog
$end
$timescale
	100ps
$end
$scope module tb_counter $end
$var wire 1 ! count_done $end
$var parameter 32 " CLK_PERIOD $end
$var reg 1 # CLK $end
$var reg 1 $ RESET $end
$scope module t0 $end
$var wire 1 # clk $end
$var wire 1 $ rst $end
$var reg 8 % cnt [7:0] $end
$var reg 1 ! count_done $end
$upscope $end
$upscope $end
$enddefinitions $end
$comment Show the parameter values. $end
$dumpall
b1010 "
$end
#0
$dumpvars
bx %
1$
0#
x!
$end
#50
b0 %
0!
1#
#100
0#
#150
1#
#200
0#
#250
1#
#300
0#
#350
1#
#400
0#
#450
1#
#500
0#
#550
1#
#600
0#
#650
1#
#700
0#
#750
1#
#800
0#
#850
1#
#900
0#
#950
1#
#1000
0#
0$
#1050
b1 %
1#
#1100
0#
#1150
b10 %
1#
#1200
0#
#1250
b11 %
1#
#1300
0#
#1350
b100 %
1#
#1400
0#
#1450
b101 %
1#
#1500
0#
#1550
b110 %
1#
#1600
0#
#1650
b111 %
1#
#1700
0#
#1750
b1000 %
1#
#1800
0#
#1850
b1001 %
1#
#1900
0#
#1950
b1010 %
1#
#2000
0#
#2050
b0 %
1!
1#
#2100
0#
#2150
0!
b1 %
1#
#2200
0#
#2250
b10 %
1#
#2300
0#
#2350
b11 %
1#
#2400
0#
#2450
b100 %
1#
#2500
0#
#2550
b101 %
1#
#2600
0#
#2650
b110 %
1#
#2700
0#
#2750
b111 %
1#
#2800
0#
#2850
b1000 %
1#
#2900
0#
#2950
b1001 %
1#
#3000
0#
#3050
b1010 %
1#
#3100
0#
#3150
1!
b0 %
1#
#3200
0#
#3250
b1 %
0!
1#
#3300
0#
#3350
b10 %
1#
#3400
0#
#3450
b11 %
1#
#3500
0#
#3550
b100 %
1#
#3600
0#
#3650
b101 %
1#
#3700
0#
#3750
b110 %
1#
#3800
0#
#3850
b111 %
1#
#3900
0#
#3950
b1000 %
1#
#4000
0#
#4050
b1001 %
1#
#4100
0#
#4150
b1010 %
1#
#4200
0#
#4250
b0 %
1!
1#
#4300
0#
#4350
0!
b1 %
1#
#4400
0#
#4450
b10 %
1#
#4500
0#
#4550
b11 %
1#
#4600
0#
#4650
b100 %
1#
#4700
0#
#4750
b101 %
1#
#4800
0#
#4850
b110 %
1#
#4900
0#
#4950
b111 %
1#
#5000
0#
#5050
b1000 %
1#
#5100
0#
#5150
b1001 %
1#
#5200
0#
#5250
b1010 %
1#
#5300
0#
#5350
1!
b0 %
1#
#5400
0#
#5450
b1 %
0!
1#
#5500
0#
#5550
b10 %
1#
#5600
0#
#5650
b11 %
1#
#5700
0#
#5750
b100 %
1#
#5800
0#
#5850
b101 %
1#
#5900
0#
#5950
b110 %
1#
#6000
0#
#6050
b111 %
1#
#6100
0#
#6150
b1000 %
1#
#6200
0#
#6250
b1001 %
1#
#6300
0#
#6350
b1010 %
1#
#6400
0#
#6450
b0 %
1!
1#
#6500
0#
#6550
0!
b1 %
1#
#6600
0#
#6650
b10 %
1#
#6700
0#
#6750
b11 %
1#
#6800
0#
#6850
b100 %
1#
#6900
0#
#6950
b101 %
1#
#7000
0#
#7050
b110 %
1#
#7100
0#
#7150
b111 %
1#
#7200
0#
#7250
b1000 %
1#
#7300
0#
#7350
b1001 %
1#
#7400
0#
#7450
b1010 %
1#
#7500
0#
#7550
1!
b0 %
1#
#7600
0#
#7650
b1 %
0!
1#
#7700
0#
#7750
b10 %
1#
#7800
0#
#7850
b11 %
1#
#7900
0#
#7950
b100 %
1#
#8000
0#
#8050
b101 %
1#
#8100
0#
#8150
b110 %
1#
#8200
0#
#8250
b111 %
1#
#8300
0#
#8350
b1000 %
1#
#8400
0#
#8450
b1001 %
1#
#8500
0#
#8550
b1010 %
1#
#8600
0#
#8650
b0 %
1!
1#
#8700
0#
#8750
0!
b1 %
1#
#8800
0#
#8850
b10 %
1#
#8900
0#
#8950
b11 %
1#
#9000
0#
#9050
b100 %
1#
#9100
0#
#9150
b101 %
1#
#9200
0#
#9250
b110 %
1#
#9300
0#
#9350
b111 %
1#
#9400
0#
#9450
b1000 %
1#
#9500
0#
#9550
b1001 %
1#
#9600
0#
#9650
b1010 %
1#
#9700
0#
#9750
1!
b0 %
1#
#9800
0#
#9850
b1 %
0!
1#
#9900
0#
#9950
b10 %
1#
#10000
0#
#10050
b11 %
1#
#10100
0#
#10150
b100 %
1#
#10200
0#
#10250
b101 %
1#
#10300
0#
#10350
b110 %
1#
#10400
0#
#10450
b111 %
1#
#10500
0#
#10550
b1000 %
1#
#10600
0#
#10650
b1001 %
1#
#10700
0#
#10750
b1010 %
1#
#10800
0#
#10850
b0 %
1!
1#
#10900
0#
#10950
0!
b1 %
1#
